<?xml version="1.0" encoding="utf-8" standalone="yes"?>
<gff3 type="PTH">
  <struct id="4294967295">
    <list label="Path_Points">
      <struct id="2">
        <uint32 label="Conections">1</uint32>
        <uint32 label="First_Conection">0</uint32>
        <float label="X">79.484497</float>
        <float label="Y">105.440308</float>
      </struct>
      <struct id="2">
        <uint32 label="Conections">1</uint32>
        <uint32 label="First_Conection">1</uint32>
        <float label="X">79.632408</float>
        <float label="Y">112.845192</float>
      </struct>
      <struct id="2">
        <uint32 label="Conections">3</uint32>
        <uint32 label="First_Conection">2</uint32>
        <float label="X">86.453712</float>
        <float label="Y">112.332535</float>
      </struct>
      <struct id="2">
        <uint32 label="Conections">2</uint32>
        <uint32 label="First_Conection">5</uint32>
        <float label="X">86.664558</float>
        <float label="Y">107.396820</float>
      </struct>
      <struct id="2">
        <uint32 label="Conections">2</uint32>
        <uint32 label="First_Conection">7</uint32>
        <float label="X">89.998322</float>
        <float label="Y">106.978157</float>
      </struct>
      <struct id="2">
        <uint32 label="Conections">3</uint32>
        <uint32 label="First_Conection">9</uint32>
        <float label="X">90.027687</float>
        <float label="Y">114.255730</float>
      </struct>
      <struct id="2">
        <uint32 label="Conections">2</uint32>
        <uint32 label="First_Conection">12</uint32>
        <float label="X">93.749702</float>
        <float label="Y">112.889175</float>
      </struct>
      <struct id="2">
        <uint32 label="Conections">2</uint32>
        <uint32 label="First_Conection">14</uint32>
        <float label="X">94.127113</float>
        <float label="Y">106.328712</float>
      </struct>
      <struct id="2">
        <uint32 label="Conections">3</uint32>
        <uint32 label="First_Conection">16</uint32>
        <float label="X">94.405075</float>
        <float label="Y">109.887527</float>
      </struct>
      <struct id="2">
        <uint32 label="Conections">3</uint32>
        <uint32 label="First_Conection">19</uint32>
        <float label="X">100.040123</float>
        <float label="Y">110.151779</float>
      </struct>
      <struct id="2">
        <uint32 label="Conections">1</uint32>
        <uint32 label="First_Conection">22</uint32>
        <float label="X">101.081718</float>
        <float label="Y">92.425034</float>
      </struct>
      <struct id="2">
        <uint32 label="Conections">1</uint32>
        <uint32 label="First_Conection">23</uint32>
        <float label="X">101.099518</float>
        <float label="Y">84.233856</float>
      </struct>
      <struct id="2">
        <uint32 label="Conections">1</uint32>
        <uint32 label="First_Conection">24</uint32>
        <float label="X">101.588379</float>
        <float label="Y">102.986572</float>
      </struct>
      <struct id="2">
        <uint32 label="Conections">1</uint32>
        <uint32 label="First_Conection">25</uint32>
        <float label="X">102.061028</float>
        <float label="Y">76.042862</float>
      </struct>
      <struct id="2">
        <uint32 label="Conections">3</uint32>
        <uint32 label="First_Conection">26</uint32>
        <float label="X">102.596550</float>
        <float label="Y">106.983246</float>
      </struct>
      <struct id="2">
        <uint32 label="Conections">1</uint32>
        <uint32 label="First_Conection">29</uint32>
        <float label="X">102.900513</float>
        <float label="Y">117.576080</float>
      </struct>
      <struct id="2">
        <uint32 label="Conections">1</uint32>
        <uint32 label="First_Conection">30</uint32>
        <float label="X">103.275734</float>
        <float label="Y">90.348022</float>
      </struct>
      <struct id="2">
        <uint32 label="Conections">4</uint32>
        <uint32 label="First_Conection">31</uint32>
        <float label="X">104.183701</float>
        <float label="Y">78.775436</float>
      </struct>
      <struct id="2">
        <uint32 label="Conections">4</uint32>
        <uint32 label="First_Conection">35</uint32>
        <float label="X">104.581970</float>
        <float label="Y">115.303825</float>
      </struct>
      <struct id="2">
        <uint32 label="Conections">1</uint32>
        <uint32 label="First_Conection">39</uint32>
        <float label="X">104.666916</float>
        <float label="Y">135.132111</float>
      </struct>
      <struct id="2">
        <uint32 label="Conections">2</uint32>
        <uint32 label="First_Conection">40</uint32>
        <float label="X">104.703163</float>
        <float label="Y">124.935295</float>
      </struct>
      <struct id="2">
        <uint32 label="Conections">1</uint32>
        <uint32 label="First_Conection">42</uint32>
        <float label="X">104.751534</float>
        <float label="Y">128.642120</float>
      </struct>
      <struct id="2">
        <uint32 label="Conections">4</uint32>
        <uint32 label="First_Conection">43</uint32>
        <float label="X">104.849052</float>
        <float label="Y">93.589478</float>
      </struct>
      <struct id="2">
        <uint32 label="Conections">1</uint32>
        <uint32 label="First_Conection">47</uint32>
        <float label="X">104.900795</float>
        <float label="Y">111.087944</float>
      </struct>
      <struct id="2">
        <uint32 label="Conections">3</uint32>
        <uint32 label="First_Conection">48</uint32>
        <float label="X">105.071259</float>
        <float label="Y">85.951942</float>
      </struct>
      <struct id="2">
        <uint32 label="Conections">2</uint32>
        <uint32 label="First_Conection">51</uint32>
        <float label="X">106.649918</float>
        <float label="Y">135.716415</float>
      </struct>
      <struct id="2">
        <uint32 label="Conections">2</uint32>
        <uint32 label="First_Conection">53</uint32>
        <float label="X">108.177376</float>
        <float label="Y">118.396927</float>
      </struct>
      <struct id="2">
        <uint32 label="Conections">2</uint32>
        <uint32 label="First_Conection">55</uint32>
        <float label="X">108.213791</float>
        <float label="Y">133.837372</float>
      </struct>
      <struct id="2">
        <uint32 label="Conections">4</uint32>
        <uint32 label="First_Conection">57</uint32>
        <float label="X">108.640991</float>
        <float label="Y">100.253784</float>
      </struct>
      <struct id="2">
        <uint32 label="Conections">2</uint32>
        <uint32 label="First_Conection">61</uint32>
        <float label="X">108.893875</float>
        <float label="Y">127.497429</float>
      </struct>
      <struct id="2">
        <uint32 label="Conections">2</uint32>
        <uint32 label="First_Conection">63</uint32>
        <float label="X">109.226990</float>
        <float label="Y">133.077484</float>
      </struct>
      <struct id="2">
        <uint32 label="Conections">3</uint32>
        <uint32 label="First_Conection">65</uint32>
        <float label="X">109.360909</float>
        <float label="Y">124.901909</float>
      </struct>
      <struct id="2">
        <uint32 label="Conections">3</uint32>
        <uint32 label="First_Conection">68</uint32>
        <float label="X">109.571106</float>
        <float label="Y">129.298950</float>
      </struct>
      <struct id="2">
        <uint32 label="Conections">2</uint32>
        <uint32 label="First_Conection">71</uint32>
        <float label="X">109.628258</float>
        <float label="Y">104.113815</float>
      </struct>
      <struct id="2">
        <uint32 label="Conections">3</uint32>
        <uint32 label="First_Conection">73</uint32>
        <float label="X">109.653625</float>
        <float label="Y">119.801170</float>
      </struct>
      <struct id="2">
        <uint32 label="Conections">3</uint32>
        <uint32 label="First_Conection">76</uint32>
        <float label="X">109.734886</float>
        <float label="Y">77.772842</float>
      </struct>
      <struct id="2">
        <uint32 label="Conections">4</uint32>
        <uint32 label="First_Conection">79</uint32>
        <float label="X">109.833054</float>
        <float label="Y">94.022026</float>
      </struct>
      <struct id="2">
        <uint32 label="Conections">4</uint32>
        <uint32 label="First_Conection">83</uint32>
        <float label="X">109.867569</float>
        <float label="Y">86.101601</float>
      </struct>
      <struct id="2">
        <uint32 label="Conections">3</uint32>
        <uint32 label="First_Conection">87</uint32>
        <float label="X">110.047676</float>
        <float label="Y">132.003494</float>
      </struct>
      <struct id="2">
        <uint32 label="Conections">2</uint32>
        <uint32 label="First_Conection">90</uint32>
        <float label="X">110.767044</float>
        <float label="Y">133.117996</float>
      </struct>
      <struct id="2">
        <uint32 label="Conections">1</uint32>
        <uint32 label="First_Conection">92</uint32>
        <float label="X">111.777077</float>
        <float label="Y">104.941223</float>
      </struct>
      <struct id="2">
        <uint32 label="Conections">2</uint32>
        <uint32 label="First_Conection">93</uint32>
        <float label="X">111.800507</float>
        <float label="Y">133.806992</float>
      </struct>
      <struct id="2">
        <uint32 label="Conections">2</uint32>
        <uint32 label="First_Conection">95</uint32>
        <float label="X">112.606010</float>
        <float label="Y">116.813202</float>
      </struct>
      <struct id="2">
        <uint32 label="Conections">2</uint32>
        <uint32 label="First_Conection">97</uint32>
        <float label="X">113.189362</float>
        <float label="Y">136.024063</float>
      </struct>
      <struct id="2">
        <uint32 label="Conections">2</uint32>
        <uint32 label="First_Conection">99</uint32>
        <float label="X">114.501015</float>
        <float label="Y">114.940491</float>
      </struct>
      <struct id="2">
        <uint32 label="Conections">1</uint32>
        <uint32 label="First_Conection">101</uint32>
        <float label="X">114.717018</float>
        <float label="Y">109.337112</float>
      </struct>
      <struct id="2">
        <uint32 label="Conections">3</uint32>
        <uint32 label="First_Conection">102</uint32>
        <float label="X">114.749649</float>
        <float label="Y">78.274307</float>
      </struct>
      <struct id="2">
        <uint32 label="Conections">1</uint32>
        <uint32 label="First_Conection">105</uint32>
        <float label="X">114.925262</float>
        <float label="Y">129.787933</float>
      </struct>
      <struct id="2">
        <uint32 label="Conections">1</uint32>
        <uint32 label="First_Conection">106</uint32>
        <float label="X">115.237511</float>
        <float label="Y">135.927109</float>
      </struct>
      <struct id="2">
        <uint32 label="Conections">3</uint32>
        <uint32 label="First_Conection">107</uint32>
        <float label="X">115.321915</float>
        <float label="Y">86.222534</float>
      </struct>
      <struct id="2">
        <uint32 label="Conections">4</uint32>
        <uint32 label="First_Conection">110</uint32>
        <float label="X">115.441498</float>
        <float label="Y">93.603462</float>
      </struct>
      <struct id="2">
        <uint32 label="Conections">1</uint32>
        <uint32 label="First_Conection">114</uint32>
        <float label="X">116.324951</float>
        <float label="Y">90.197540</float>
      </struct>
      <struct id="2">
        <uint32 label="Conections">4</uint32>
        <uint32 label="First_Conection">115</uint32>
        <float label="X">116.401100</float>
        <float label="Y">113.415604</float>
      </struct>
      <struct id="2">
        <uint32 label="Conections">1</uint32>
        <uint32 label="First_Conection">119</uint32>
        <float label="X">116.457039</float>
        <float label="Y">75.735901</float>
      </struct>
      <struct id="2">
        <uint32 label="Conections">2</uint32>
        <uint32 label="First_Conection">120</uint32>
        <float label="X">116.981628</float>
        <float label="Y">101.388153</float>
      </struct>
      <struct id="2">
        <uint32 label="Conections">2</uint32>
        <uint32 label="First_Conection">122</uint32>
        <float label="X">117.534927</float>
        <float label="Y">117.127457</float>
      </struct>
      <struct id="2">
        <uint32 label="Conections">1</uint32>
        <uint32 label="First_Conection">124</uint32>
        <float label="X">118.075439</float>
        <float label="Y">118.138924</float>
      </struct>
      <struct id="2">
        <uint32 label="Conections">3</uint32>
        <uint32 label="First_Conection">125</uint32>
        <float label="X">118.670280</float>
        <float label="Y">109.692261</float>
      </struct>
      <struct id="2">
        <uint32 label="Conections">2</uint32>
        <uint32 label="First_Conection">128</uint32>
        <float label="X">118.693779</float>
        <float label="Y">93.308823</float>
      </struct>
      <struct id="2">
        <uint32 label="Conections">1</uint32>
        <uint32 label="First_Conection">130</uint32>
        <float label="X">118.729141</float>
        <float label="Y">90.922325</float>
      </struct>
      <struct id="2">
        <uint32 label="Conections">1</uint32>
        <uint32 label="First_Conection">131</uint32>
        <float label="X">124.733032</float>
        <float label="Y">115.234978</float>
      </struct>
      <struct id="2">
        <uint32 label="Conections">3</uint32>
        <uint32 label="First_Conection">132</uint32>
        <float label="X">124.933517</float>
        <float label="Y">109.863266</float>
      </struct>
      <struct id="2">
        <uint32 label="Conections">3</uint32>
        <uint32 label="First_Conection">135</uint32>
        <float label="X">125.858345</float>
        <float label="Y">111.936798</float>
      </struct>
      <struct id="2">
        <uint32 label="Conections">2</uint32>
        <uint32 label="First_Conection">138</uint32>
        <float label="X">125.985153</float>
        <float label="Y">107.430046</float>
      </struct>
      <struct id="2">
        <uint32 label="Conections">2</uint32>
        <uint32 label="First_Conection">140</uint32>
        <float label="X">129.758133</float>
        <float label="Y">106.962631</float>
      </struct>
      <struct id="2">
        <uint32 label="Conections">2</uint32>
        <uint32 label="First_Conection">142</uint32>
        <float label="X">131.392426</float>
        <float label="Y">112.529228</float>
      </struct>
      <struct id="2">
        <uint32 label="Conections">1</uint32>
        <uint32 label="First_Conection">144</uint32>
        <float label="X">134.193344</float>
        <float label="Y">105.091019</float>
      </struct>
      <struct id="2">
        <uint32 label="Conections">3</uint32>
        <uint32 label="First_Conection">145</uint32>
        <float label="X">134.525177</float>
        <float label="Y">107.013786</float>
      </struct>
      <struct id="2">
        <uint32 label="Conections">3</uint32>
        <uint32 label="First_Conection">148</uint32>
        <float label="X">136.309113</float>
        <float label="Y">112.291039</float>
      </struct>
      <struct id="2">
        <uint32 label="Conections">1</uint32>
        <uint32 label="First_Conection">151</uint32>
        <float label="X">136.325668</float>
        <float label="Y">115.316315</float>
      </struct>
      <struct id="2">
        <uint32 label="Conections">3</uint32>
        <uint32 label="First_Conection">152</uint32>
        <float label="X">139.816925</float>
        <float label="Y">110.173973</float>
      </struct>
      <struct id="2">
        <uint32 label="Conections">1</uint32>
        <uint32 label="First_Conection">155</uint32>
        <float label="X">144.251465</float>
        <float label="Y">110.252464</float>
      </struct>
    </list>
    <list label="Path_Conections">
      <struct id="3">
        <uint32 label="Destination">3</uint32>
      </struct>
      <struct id="3">
        <uint32 label="Destination">2</uint32>
      </struct>
      <struct id="3">
        <uint32 label="Destination">1</uint32>
      </struct>
      <struct id="3">
        <uint32 label="Destination">3</uint32>
      </struct>
      <struct id="3">
        <uint32 label="Destination">5</uint32>
      </struct>
      <struct id="3">
        <uint32 label="Destination">0</uint32>
      </struct>
      <struct id="3">
        <uint32 label="Destination">2</uint32>
      </struct>
      <struct id="3">
        <uint32 label="Destination">5</uint32>
      </struct>
      <struct id="3">
        <uint32 label="Destination">7</uint32>
      </struct>
      <struct id="3">
        <uint32 label="Destination">2</uint32>
      </struct>
      <struct id="3">
        <uint32 label="Destination">4</uint32>
      </struct>
      <struct id="3">
        <uint32 label="Destination">6</uint32>
      </struct>
      <struct id="3">
        <uint32 label="Destination">5</uint32>
      </struct>
      <struct id="3">
        <uint32 label="Destination">8</uint32>
      </struct>
      <struct id="3">
        <uint32 label="Destination">4</uint32>
      </struct>
      <struct id="3">
        <uint32 label="Destination">8</uint32>
      </struct>
      <struct id="3">
        <uint32 label="Destination">6</uint32>
      </struct>
      <struct id="3">
        <uint32 label="Destination">7</uint32>
      </struct>
      <struct id="3">
        <uint32 label="Destination">9</uint32>
      </struct>
      <struct id="3">
        <uint32 label="Destination">8</uint32>
      </struct>
      <struct id="3">
        <uint32 label="Destination">18</uint32>
      </struct>
      <struct id="3">
        <uint32 label="Destination">14</uint32>
      </struct>
      <struct id="3">
        <uint32 label="Destination">22</uint32>
      </struct>
      <struct id="3">
        <uint32 label="Destination">17</uint32>
      </struct>
      <struct id="3">
        <uint32 label="Destination">14</uint32>
      </struct>
      <struct id="3">
        <uint32 label="Destination">17</uint32>
      </struct>
      <struct id="3">
        <uint32 label="Destination">9</uint32>
      </struct>
      <struct id="3">
        <uint32 label="Destination">12</uint32>
      </struct>
      <struct id="3">
        <uint32 label="Destination">28</uint32>
      </struct>
      <struct id="3">
        <uint32 label="Destination">18</uint32>
      </struct>
      <struct id="3">
        <uint32 label="Destination">22</uint32>
      </struct>
      <struct id="3">
        <uint32 label="Destination">11</uint32>
      </struct>
      <struct id="3">
        <uint32 label="Destination">13</uint32>
      </struct>
      <struct id="3">
        <uint32 label="Destination">35</uint32>
      </struct>
      <struct id="3">
        <uint32 label="Destination">24</uint32>
      </struct>
      <struct id="3">
        <uint32 label="Destination">9</uint32>
      </struct>
      <struct id="3">
        <uint32 label="Destination">15</uint32>
      </struct>
      <struct id="3">
        <uint32 label="Destination">23</uint32>
      </struct>
      <struct id="3">
        <uint32 label="Destination">26</uint32>
      </struct>
      <struct id="3">
        <uint32 label="Destination">25</uint32>
      </struct>
      <struct id="3">
        <uint32 label="Destination">31</uint32>
      </struct>
      <struct id="3">
        <uint32 label="Destination">21</uint32>
      </struct>
      <struct id="3">
        <uint32 label="Destination">20</uint32>
      </struct>
      <struct id="3">
        <uint32 label="Destination">10</uint32>
      </struct>
      <struct id="3">
        <uint32 label="Destination">16</uint32>
      </struct>
      <struct id="3">
        <uint32 label="Destination">36</uint32>
      </struct>
      <struct id="3">
        <uint32 label="Destination">24</uint32>
      </struct>
      <struct id="3">
        <uint32 label="Destination">18</uint32>
      </struct>
      <struct id="3">
        <uint32 label="Destination">17</uint32>
      </struct>
      <struct id="3">
        <uint32 label="Destination">22</uint32>
      </struct>
      <struct id="3">
        <uint32 label="Destination">37</uint32>
      </struct>
      <struct id="3">
        <uint32 label="Destination">19</uint32>
      </struct>
      <struct id="3">
        <uint32 label="Destination">27</uint32>
      </struct>
      <struct id="3">
        <uint32 label="Destination">18</uint32>
      </struct>
      <struct id="3">
        <uint32 label="Destination">34</uint32>
      </struct>
      <struct id="3">
        <uint32 label="Destination">25</uint32>
      </struct>
      <struct id="3">
        <uint32 label="Destination">30</uint32>
      </struct>
      <struct id="3">
        <uint32 label="Destination">14</uint32>
      </struct>
      <struct id="3">
        <uint32 label="Destination">33</uint32>
      </struct>
      <struct id="3">
        <uint32 label="Destination">54</uint32>
      </struct>
      <struct id="3">
        <uint32 label="Destination">36</uint32>
      </struct>
      <struct id="3">
        <uint32 label="Destination">32</uint32>
      </struct>
      <struct id="3">
        <uint32 label="Destination">31</uint32>
      </struct>
      <struct id="3">
        <uint32 label="Destination">27</uint32>
      </struct>
      <struct id="3">
        <uint32 label="Destination">38</uint32>
      </struct>
      <struct id="3">
        <uint32 label="Destination">20</uint32>
      </struct>
      <struct id="3">
        <uint32 label="Destination">29</uint32>
      </struct>
      <struct id="3">
        <uint32 label="Destination">34</uint32>
      </struct>
      <struct id="3">
        <uint32 label="Destination">29</uint32>
      </struct>
      <struct id="3">
        <uint32 label="Destination">38</uint32>
      </struct>
      <struct id="3">
        <uint32 label="Destination">47</uint32>
      </struct>
      <struct id="3">
        <uint32 label="Destination">28</uint32>
      </struct>
      <struct id="3">
        <uint32 label="Destination">40</uint32>
      </struct>
      <struct id="3">
        <uint32 label="Destination">26</uint32>
      </struct>
      <struct id="3">
        <uint32 label="Destination">31</uint32>
      </struct>
      <struct id="3">
        <uint32 label="Destination">42</uint32>
      </struct>
      <struct id="3">
        <uint32 label="Destination">17</uint32>
      </struct>
      <struct id="3">
        <uint32 label="Destination">37</uint32>
      </struct>
      <struct id="3">
        <uint32 label="Destination">46</uint32>
      </struct>
      <struct id="3">
        <uint32 label="Destination">22</uint32>
      </struct>
      <struct id="3">
        <uint32 label="Destination">28</uint32>
      </struct>
      <struct id="3">
        <uint32 label="Destination">37</uint32>
      </struct>
      <struct id="3">
        <uint32 label="Destination">50</uint32>
      </struct>
      <struct id="3">
        <uint32 label="Destination">24</uint32>
      </struct>
      <struct id="3">
        <uint32 label="Destination">35</uint32>
      </struct>
      <struct id="3">
        <uint32 label="Destination">36</uint32>
      </struct>
      <struct id="3">
        <uint32 label="Destination">49</uint32>
      </struct>
      <struct id="3">
        <uint32 label="Destination">30</uint32>
      </struct>
      <struct id="3">
        <uint32 label="Destination">32</uint32>
      </struct>
      <struct id="3">
        <uint32 label="Destination">39</uint32>
      </struct>
      <struct id="3">
        <uint32 label="Destination">38</uint32>
      </struct>
      <struct id="3">
        <uint32 label="Destination">41</uint32>
      </struct>
      <struct id="3">
        <uint32 label="Destination">33</uint32>
      </struct>
      <struct id="3">
        <uint32 label="Destination">39</uint32>
      </struct>
      <struct id="3">
        <uint32 label="Destination">43</uint32>
      </struct>
      <struct id="3">
        <uint32 label="Destination">34</uint32>
      </struct>
      <struct id="3">
        <uint32 label="Destination">44</uint32>
      </struct>
      <struct id="3">
        <uint32 label="Destination">41</uint32>
      </struct>
      <struct id="3">
        <uint32 label="Destination">48</uint32>
      </struct>
      <struct id="3">
        <uint32 label="Destination">42</uint32>
      </struct>
      <struct id="3">
        <uint32 label="Destination">52</uint32>
      </struct>
      <struct id="3">
        <uint32 label="Destination">52</uint32>
      </struct>
      <struct id="3">
        <uint32 label="Destination">35</uint32>
      </struct>
      <struct id="3">
        <uint32 label="Destination">49</uint32>
      </struct>
      <struct id="3">
        <uint32 label="Destination">53</uint32>
      </struct>
      <struct id="3">
        <uint32 label="Destination">32</uint32>
      </struct>
      <struct id="3">
        <uint32 label="Destination">43</uint32>
      </struct>
      <struct id="3">
        <uint32 label="Destination">37</uint32>
      </struct>
      <struct id="3">
        <uint32 label="Destination">46</uint32>
      </struct>
      <struct id="3">
        <uint32 label="Destination">50</uint32>
      </struct>
      <struct id="3">
        <uint32 label="Destination">36</uint32>
      </struct>
      <struct id="3">
        <uint32 label="Destination">49</uint32>
      </struct>
      <struct id="3">
        <uint32 label="Destination">51</uint32>
      </struct>
      <struct id="3">
        <uint32 label="Destination">58</uint32>
      </struct>
      <struct id="3">
        <uint32 label="Destination">50</uint32>
      </struct>
      <struct id="3">
        <uint32 label="Destination">44</uint32>
      </struct>
      <struct id="3">
        <uint32 label="Destination">45</uint32>
      </struct>
      <struct id="3">
        <uint32 label="Destination">55</uint32>
      </struct>
      <struct id="3">
        <uint32 label="Destination">57</uint32>
      </struct>
      <struct id="3">
        <uint32 label="Destination">46</uint32>
      </struct>
      <struct id="3">
        <uint32 label="Destination">28</uint32>
      </struct>
      <struct id="3">
        <uint32 label="Destination">57</uint32>
      </struct>
      <struct id="3">
        <uint32 label="Destination">52</uint32>
      </struct>
      <struct id="3">
        <uint32 label="Destination">56</uint32>
      </struct>
      <struct id="3">
        <uint32 label="Destination">55</uint32>
      </struct>
      <struct id="3">
        <uint32 label="Destination">52</uint32>
      </struct>
      <struct id="3">
        <uint32 label="Destination">54</uint32>
      </struct>
      <struct id="3">
        <uint32 label="Destination">61</uint32>
      </struct>
      <struct id="3">
        <uint32 label="Destination">50</uint32>
      </struct>
      <struct id="3">
        <uint32 label="Destination">59</uint32>
      </struct>
      <struct id="3">
        <uint32 label="Destination">58</uint32>
      </struct>
      <struct id="3">
        <uint32 label="Destination">62</uint32>
      </struct>
      <struct id="3">
        <uint32 label="Destination">57</uint32>
      </struct>
      <struct id="3">
        <uint32 label="Destination">62</uint32>
      </struct>
      <struct id="3">
        <uint32 label="Destination">63</uint32>
      </struct>
      <struct id="3">
        <uint32 label="Destination">60</uint32>
      </struct>
      <struct id="3">
        <uint32 label="Destination">61</uint32>
      </struct>
      <struct id="3">
        <uint32 label="Destination">65</uint32>
      </struct>
      <struct id="3">
        <uint32 label="Destination">61</uint32>
      </struct>
      <struct id="3">
        <uint32 label="Destination">64</uint32>
      </struct>
      <struct id="3">
        <uint32 label="Destination">63</uint32>
      </struct>
      <struct id="3">
        <uint32 label="Destination">67</uint32>
      </struct>
      <struct id="3">
        <uint32 label="Destination">62</uint32>
      </struct>
      <struct id="3">
        <uint32 label="Destination">68</uint32>
      </struct>
      <struct id="3">
        <uint32 label="Destination">67</uint32>
      </struct>
      <struct id="3">
        <uint32 label="Destination">64</uint32>
      </struct>
      <struct id="3">
        <uint32 label="Destination">66</uint32>
      </struct>
      <struct id="3">
        <uint32 label="Destination">70</uint32>
      </struct>
      <struct id="3">
        <uint32 label="Destination">65</uint32>
      </struct>
      <struct id="3">
        <uint32 label="Destination">69</uint32>
      </struct>
      <struct id="3">
        <uint32 label="Destination">70</uint32>
      </struct>
      <struct id="3">
        <uint32 label="Destination">68</uint32>
      </struct>
      <struct id="3">
        <uint32 label="Destination">67</uint32>
      </struct>
      <struct id="3">
        <uint32 label="Destination">68</uint32>
      </struct>
      <struct id="3">
        <uint32 label="Destination">71</uint32>
      </struct>
      <struct id="3">
        <uint32 label="Destination">70</uint32>
      </struct>
    </list>
  </struct>
</gff3>
